{
  "archive": "archive",
  "audio": "music",
  "bash": "bash",
  "binary": "binary",
  "c": "c",
  "clojure": "clojure",
  "coffeescript": "coffeescript",
  "cpp": "cpp",
  "csharp": "csharp",
  "css": "css",
  "dart": "dart",
  "database": "database",
  "diff": "diff",
  "directory": "folder-default",
  "ejs": "html",
  "epub": "epub",
  "erb_html": "ruby",
  "excel": "excel",
  "executable": "executable",
  "gif": "gif",
  "groovy": "script",
  "haskell": "haskell",
  "html": "html",
  "hx": "haxe",
  "illustrator": "illustrator",
  "image": "image",
  "image_file": "image_file",
  "java": "java",
  "javascript": "javascript",
  "jpeg": "jpg",
  "jpg": "jpg",
  "js": "javascript",
  "json": "json",
  "jsx": "react",
  "less": "less",
  "library": "library",
  "lua": "lua",
  "markdown": "markdown",
  "office": "office",
  "pdf": "pdf",
  "perl": "perl",
  "photoshop": "photoshop",
  "php": "php",
  "png": "png",
  "powerpoint": "powerpoint",
  "properties": "settings",
  "python": "python",
  "ruby": "ruby",
  "sass": "sass",
  "scala": "scala",
  "scss": "sass",
  "sql": "mysql",
  "sqlite": "sqlite",
  "stylus": "stylus",
  "svg": "svg",
  "txt": "text",
  "unknown": "text",
  "vb": "script",
  "vbscript": "script",
  "video": "video",
  "word": "word",
  "xml": "xml",
  "yaml": "settings",
  "zip": "zip"
}
